kindle_to_markdown/__init__.py
kindle_to_markdown/__main__.py
kindle_to_markdown/languages.py
kindle_to_markdown-0.0.3.dist-info/LICENSE.txt
kindle_to_markdown-0.0.3.dist-info/METADATA
kindle_to_markdown-0.0.3.dist-info/WHEEL
kindle_to_markdown-0.0.3.dist-info/entry_points.txt
kindle_to_markdown-0.0.3.dist-info/RECORD
