Metadata-Version: 2.1
Name: kindle_to_markdown
Version: 0.0.3
Summary: A simple program to convert Kindle HTML annotations to a Markdown file.
Home-page: https://github.com/BastiTee/kindle-to-markdown
License: Apache 2.0
Keywords: kindle,markdown,converter,python
Author: Basti Tee
Author-email: basti.tee@icloud.com
Maintainer: Basti Tee
Maintainer-email: basti.tee@icloud.com
Requires-Python: >=3.9.0,<4.0.0
Classifier: Development Status :: 4 - Beta
Classifier: Intended Audience :: Developers
Classifier: License :: OSI Approved :: Apache Software License
Classifier: License :: Other/Proprietary License
Classifier: Natural Language :: English
Classifier: Programming Language :: Python
Classifier: Programming Language :: Python :: 3
Classifier: Programming Language :: Python :: 3.9
Classifier: Programming Language :: Python :: 3.10
Classifier: Programming Language :: Python :: 3.11
Classifier: Programming Language :: Python :: 3.12
Classifier: Programming Language :: Python :: 3.13
Requires-Dist: beautifulsoup4 (>=4.12.3,<5.0.0)
Requires-Dist: click (>=8.1.7,<9.0.0)
Requires-Dist: twine (>=6.0.1,<7.0.0)
Project-URL: Repository, https://github.com/BastiTee/kindle-to-markdown
